prefixtrie/__init__.py
prefixtrie/_impl.cpp
prefixtrie/_impl.cpython-314t-x86_64-linux-gnu.so
prefixtrie/_impl.pyx
prefixtrie/_version.py
prefixtrie/simd_compare.h
prefixtrie-1.1.0.dist-info/METADATA
prefixtrie-1.1.0.dist-info/WHEEL
prefixtrie-1.1.0.dist-info/top_level.txt
prefixtrie-1.1.0.dist-info/RECORD
prefixtrie-1.1.0.dist-info/licenses/LICENSE
