Metadata-Version: 2.4
Name: prefixtrie
Version: 1.1.0
Summary: A cython implementation of a prefix trie data structure for fast fuzzy matching.
Author-email: Austin Varela <austinv11@gmail.com>
Maintainer-email: Austin Varela <austinv11@gmail.com>
License-Expression: MIT
Project-URL: Homepage, https://github.com/austinv11/PrefixTrie
Project-URL: Repository, https://github.com/austinv11/PrefixTrie
Project-URL: Documentation, https://austinv11.github.io/PrefixTrie
Project-URL: Bug Tracker, https://github.com/austinv11/PrefixTrie/issues
Project-URL: Changelog, https://github.com/austinv11/PrefixTrie/releases
Keywords: trie,prefix-trie,fuzzy-matching,string-matching,bioinformatics,fuzzy-search
Classifier: Development Status :: 5 - Production/Stable
Classifier: Intended Audience :: Developers
Classifier: Intended Audience :: Science/Research
Classifier: Operating System :: OS Independent
Classifier: Programming Language :: Python :: 3
Classifier: Programming Language :: Python :: 3.10
Classifier: Programming Language :: Python :: 3.11
Classifier: Programming Language :: Python :: 3.12
Classifier: Programming Language :: Python :: 3.13
Classifier: Programming Language :: Cython
Classifier: Programming Language :: C++
Classifier: Topic :: Scientific/Engineering :: Bio-Informatics
Classifier: Topic :: Software Development :: Libraries :: Python Modules
Classifier: Topic :: Text Processing
Requires-Python: >=3.10
License-File: LICENSE
Provides-Extra: dev
Requires-Dist: matplotlib>=3.10.6; extra == "dev"
Requires-Dist: numpy>=2.2.6; extra == "dev"
Requires-Dist: regex>=2025.9.1; extra == "dev"
Requires-Dist: symspellpy>=6.9.0; extra == "dev"
Requires-Dist: thefuzz[speedup]>=0.22.1; extra == "dev"
Requires-Dist: rapidfuzz>=3.0; extra == "dev"
Requires-Dist: fuzzysearch>=0.8.0; extra == "dev"
Requires-Dist: setuptools>=80; extra == "dev"
Requires-Dist: cython>=3.0; extra == "dev"
Requires-Dist: mkdocs-material>=9.6.18; extra == "dev"
Requires-Dist: mkdocs>=1.6.1; extra == "dev"
Requires-Dist: pytest>=8.4.1; extra == "dev"
Requires-Dist: mkdocstrings[python]>=0.25; extra == "dev"
Requires-Dist: mkdocstrings-python>=1.0; extra == "dev"
Dynamic: license-file
